hetio/__init__.py
hetio/abbreviation.py
hetio/hetnet.py
hetio/matrix.py
hetio/neo4j.py
hetio/pathtools.py
hetio/permute.py
hetio/readwrite.py
hetio/stats.py
hetio-0.2.11.dist-info/LICENSE.md
hetio-0.2.11.dist-info/METADATA
hetio-0.2.11.dist-info/WHEEL
hetio-0.2.11.dist-info/top_level.txt
hetio-0.2.11.dist-info/RECORD
