Metadata-Version: 2.1
Name: hetio
Version: 0.2.11
Summary: Hetnets in Python
Home-page: https://github.com/hetio/hetio
Author: Daniel Himmelstein
Author-email: daniel.himmelstein@gmail.com
License: CC0 1.0
Keywords: hetnet graph heterogeneous network neo4j hetio
Platform: UNKNOWN
Classifier: Intended Audience :: Science/Research
Classifier: Topic :: Scientific/Engineering :: Bio-Informatics
Classifier: Topic :: Scientific/Engineering :: Information Analysis
Classifier: License :: CC0 1.0 Universal (CC0 1.0) Public Domain Dedication
Classifier: Programming Language :: Python :: 3
Classifier: Programming Language :: Python :: 3 :: Only
Classifier: Programming Language :: Python :: 3.4
Classifier: Programming Language :: Python :: 3.5
Classifier: Programming Language :: Python :: 3.6
Requires-Python: >=3.4
Requires-Dist: regex
Provides-Extra: matrix
Requires-Dist: numpy ; extra == 'matrix'
Requires-Dist: scipy ; extra == 'matrix'
Provides-Extra: neo4j
Requires-Dist: pandas ; extra == 'neo4j'
Requires-Dist: py2neo ; extra == 'neo4j'
Requires-Dist: tqdm ; extra == 'neo4j'
Provides-Extra: stats
Requires-Dist: pandas ; extra == 'stats'
Requires-Dist: matplotlib ; extra == 'stats'
Requires-Dist: seaborn ; extra == 'stats'
Provides-Extra: test
Requires-Dist: numpy ; extra == 'test'
Requires-Dist: scipy ; extra == 'test'
Requires-Dist: neo4j ; extra == 'test'
Requires-Dist: py2neo ; extra == 'test'
Requires-Dist: pandas ; extra == 'test'
Requires-Dist: tqdm ; extra == 'test'
